lml/__init__.py
lml/_version.py
lml/loader.py
lml/plugin.py
lml/utils.py
lml-0.0.8.dist-info/LICENSE
lml-0.0.8.dist-info/METADATA
lml-0.0.8.dist-info/WHEEL
lml-0.0.8.dist-info/top_level.txt
lml-0.0.8.dist-info/RECORD
