Metadata-Version: 2.1
Name: lml
Version: 0.0.8
Summary: Load me later. A lazy plugin management system.
Home-page: https://github.com/chfw/lml
Author: C.W.
Author-email: wangc_2011@hotmail.com
License: New BSD
Download-URL: https://github.com/chfw/lml/archive/0.0.8.tar.gz
Keywords: python
Platform: UNKNOWN
Classifier: Topic :: Software Development :: Libraries
Classifier: Programming Language :: Python
Classifier: Intended Audience :: Developers
Classifier: Programming Language :: Python :: 2.6
Classifier: Programming Language :: Python :: 2.7
Classifier: Programming Language :: Python :: 3.3
Classifier: Programming Language :: Python :: 3.4
Classifier: Programming Language :: Python :: 3.5
Classifier: Programming Language :: Python :: 3.6
